README.md
setup.py
gromacs/__init__.py
gromacs.egg-info/PKG-INFO
gromacs.egg-info/SOURCES.txt
gromacs.egg-info/dependency_links.txt
gromacs.egg-info/top_level.txt