Metadata-Version: 1.0
Name: gromacs
Version: 0.0.0
Summary: GROMACS bindings package
Home-page: https://github.com/kassonlab/gromacs-gmxapi
Author: M. Eric Irrgang
Author-email: ericirrgang@gmail.com
License: UNKNOWN
Platform: UNKNOWN
